py4openag/__init__.py
py4openag/py4openag.py
py4openag-0.0.2.2.dist-info/LICENSE
py4openag-0.0.2.2.dist-info/METADATA
py4openag-0.0.2.2.dist-info/WHEEL
py4openag-0.0.2.2.dist-info/top_level.txt
py4openag-0.0.2.2.dist-info/RECORD
