Metadata-Version: 2.1
Name: py4openag
Version: 0.0.2.2
Summary: This open-source package aims to establish the ML4Ops pipeline from public databases to integrated analytics for agriculture. It provides  a variety of functions  to study climate trends and simplify the calculation of commonly used metrics in agriculture. 
Home-page: https://github.com/niveditapatel/py4openag
Author: Nivedita Patel
Author-email: patelnivedita@icloud.com
License: MIT
Platform: UNKNOWN
Classifier: Programming Language :: Python :: 3
Classifier: Operating System :: OS Independent
Requires-Python: >=3.6
License-File: LICENSE
Requires-Dist: pandas
Requires-Dist: datetime
Requires-Dist: sklearn
Requires-Dist: matplotlib
Requires-Dist: ipyleaflet (>=0.13.0)
Requires-Dist: ipywidgets (>=7.5.0)
Requires-Dist: random2
